LICENSE
MANIFEST.in
README
README.rst
setup.py
django_pendulum.egg-info/PKG-INFO
django_pendulum.egg-info/SOURCES.txt
django_pendulum.egg-info/dependency_links.txt
django_pendulum.egg-info/not-zip-safe
django_pendulum.egg-info/top_level.txt
pendulum/__init__.py
pendulum/admin.py
pendulum/fields.py
pendulum/forms.py
pendulum/middleware.py
pendulum/models.py
pendulum/pendulum.kpf
pendulum/urls.py
pendulum/utils.py
pendulum/views.py
pendulum/widgets.py
pendulum/fixtures/activities.json
pendulum/fixtures/entries.json
pendulum/fixtures/projects.json
pendulum/fixtures/users.json
pendulum/management/__init__.py
pendulum/management/commands/__init__.py
pendulum/management/commands/create_pendulum_group.py
pendulum/media/css/jquery-ui.css
pendulum/media/css/style.css
pendulum/media/img/222222_11x11_icon_arrows_leftright.gif
pendulum/media/img/222222_11x11_icon_arrows_updown.gif
pendulum/media/img/222222_11x11_icon_close.gif
pendulum/media/img/222222_11x11_icon_doc.gif
pendulum/media/img/222222_11x11_icon_folder_closed.gif
pendulum/media/img/222222_11x11_icon_folder_open.gif
pendulum/media/img/222222_11x11_icon_minus.gif
pendulum/media/img/222222_11x11_icon_plus.gif
pendulum/media/img/222222_11x11_icon_resize_se.gif
pendulum/media/img/222222_35x9_colorpicker_indicator.gif.gif
pendulum/media/img/222222_7x7_arrow_down.gif
pendulum/media/img/222222_7x7_arrow_left.gif
pendulum/media/img/222222_7x7_arrow_right.gif
pendulum/media/img/222222_7x7_arrow_up.gif
pendulum/media/img/454545_11x11_icon_arrows_leftright.gif
pendulum/media/img/454545_11x11_icon_arrows_updown.gif
pendulum/media/img/454545_11x11_icon_close.gif
pendulum/media/img/454545_11x11_icon_doc.gif
pendulum/media/img/454545_11x11_icon_folder_closed.gif
pendulum/media/img/454545_11x11_icon_folder_open.gif
pendulum/media/img/454545_11x11_icon_minus.gif
pendulum/media/img/454545_11x11_icon_plus.gif
pendulum/media/img/454545_7x7_arrow_down.gif
pendulum/media/img/454545_7x7_arrow_left.gif
pendulum/media/img/454545_7x7_arrow_right.gif
pendulum/media/img/454545_7x7_arrow_up.gif
pendulum/media/img/888888_11x11_icon_arrows_leftright.gif
pendulum/media/img/888888_11x11_icon_arrows_updown.gif
