Metadata-Version: 1.0
Name: django-pendulum
Version: 0.1.6-pre4
Summary: A simple timeclock/timecard application for use in Django-powered Web sites.
Home-page: http://bitbucket.org/codekoala/django-pendulum/
Author: Josh VanderLinden
Author-email: codekoala@gmail.com
License: MIT
Keywords: django,time tracking,pendulum
Platform: UNKNOWN
Classifier: Development Status :: 4 - Beta
Classifier: Environment :: Web Environment
Classifier: Framework :: Django
Classifier: Intended Audience :: Developers
Classifier: Intended Audience :: End Users/Desktop
Classifier: License :: OSI Approved :: MIT License
Classifier: Natural Language :: English
Classifier: Operating System :: OS Independent
Classifier: Programming Language :: Python
Classifier: Topic :: Internet :: WWW/HTTP :: Dynamic Content
Classifier: Topic :: Office/Business :: Financial :: Accounting
Classifier: Topic :: Office/Business :: Scheduling
